poetry_1_conflict_svltv32/__init__.py
poetry_1_conflict_svltv32/conflict1.py
poetry_1_conflict_svltv32-0.5.0.dist-info/WHEEL
poetry_1_conflict_svltv32-0.5.0.dist-info/METADATA
poetry_1_conflict_svltv32-0.5.0.dist-info/RECORD
