Metadata-Version: 2.1
Name: poetry-1-conflict-svltv32
Version: 0.5.0
Summary: 
Author: sdfasdf
Requires-Python: >=3.8,<4.0
Classifier: Programming Language :: Python :: 3
Classifier: Programming Language :: Python :: 3.8
Classifier: Programming Language :: Python :: 3.9
Requires-Dist: poetry_2_conflict_svltv32
